foliant/preprocessors/imgcaptions.py
foliantcontrib.imgcaptions-1.0.4.dist-info/LICENSE
foliantcontrib.imgcaptions-1.0.4.dist-info/METADATA
foliantcontrib.imgcaptions-1.0.4.dist-info/WHEEL
foliantcontrib.imgcaptions-1.0.4.dist-info/top_level.txt
foliantcontrib.imgcaptions-1.0.4.dist-info/RECORD
