Metadata-Version: 2.1
Name: foliantcontrib.imgcaptions
Version: 1.0.4
Summary: Preprocessor for Foliant for adding visible captions to images.
Home-page: https://github.com/foliant-docs/foliantcontrib.imgcaptions
Author: Artemy Lomov
Author-email: artemy@lomov.ru
License: MIT
Platform: any
Classifier: Development Status :: 5 - Production/Stable
Classifier: Environment :: Console
Classifier: Intended Audience :: Developers
Classifier: License :: OSI Approved :: MIT License
Classifier: Operating System :: OS Independent
Classifier: Programming Language :: Python
Classifier: Topic :: Documentation
Classifier: Topic :: Utilities
License-File: LICENSE
Requires-Dist: foliant (>=1.0.4)
